check_jvm/__init__.py
check_jvm/__main__.py
check_jvm/app.py
check_jvm/java_version.py
check_jvm/logger.py
check_jvm/py.typed
check_jvm-0.1.3.dist-info/LICENSE
check_jvm-0.1.3.dist-info/METADATA
check_jvm-0.1.3.dist-info/WHEEL
check_jvm-0.1.3.dist-info/entry_points.txt
check_jvm-0.1.3.dist-info/RECORD
